esty/__init__.py
esty/parse.py
esty-0.1.0.dist-info/METADATA
esty-0.1.0.dist-info/WHEEL
esty-0.1.0.dist-info/RECORD
